django_admin_groupby/__init__.py
django_admin_groupby/admin.py
django_admin_groupby/aggregations.py
django_admin_groupby/apps.py
django_admin_groupby/templates/admin/group_by_filter.html
django_admin_groupby/templates/admin/grouped_change_list.html
django_admin_groupby/templatetags/__init__.py
django_admin_groupby/templatetags/django_admin_groupby.py
django_admin_groupby-1.1.dist-info/licenses/LICENSE
django_admin_groupby-1.1.dist-info/METADATA
django_admin_groupby-1.1.dist-info/WHEEL
django_admin_groupby-1.1.dist-info/top_level.txt
django_admin_groupby-1.1.dist-info/RECORD
