Metadata-Version: 2.4
Name: django-admin-groupby
Version: 1.1
Summary: A Django app that extends the admin interface with group-by functionality
Home-page: https://github.com/numegil/django-admin-groupby
Author: Alexei Gousev
Author-email: numegil@gmail.com
Project-URL: Bug Tracker, https://github.com/numegil/django-admin-groupby/issues
Project-URL: Source Code, https://github.com/numegil/django-admin-groupby
Project-URL: Documentation, https://github.com/numegil/django-admin-groupby#readme
Project-URL: Changelog, https://github.com/numegil/django-admin-groupby/blob/main/CHANGELOG.md
Keywords: django admin group-by groupby aggregate aggregation sum count average
Classifier: Development Status :: 5 - Production/Stable
Classifier: Environment :: Web Environment
Classifier: Framework :: Django
Classifier: Framework :: Django :: 3.2
Classifier: Framework :: Django :: 4.0
Classifier: Framework :: Django :: 4.1
Classifier: Framework :: Django :: 4.2
Classifier: Framework :: Django :: 5.0
Classifier: Framework :: Django :: 5.1
Classifier: Framework :: Django :: 5.2
Classifier: Intended Audience :: Developers
Classifier: License :: OSI Approved :: MIT License
Classifier: Operating System :: OS Independent
Classifier: Programming Language :: Python
Classifier: Programming Language :: Python :: 3
Classifier: Programming Language :: Python :: 3.8
Classifier: Programming Language :: Python :: 3.9
Classifier: Programming Language :: Python :: 3.10
Classifier: Programming Language :: Python :: 3.11
Classifier: Programming Language :: Python :: 3.12
Classifier: Topic :: Internet :: WWW/HTTP
Classifier: Topic :: Software Development :: Libraries :: Application Frameworks
Classifier: Topic :: Software Development :: Libraries :: Python Modules
Requires-Python: >=3.8
License-File: LICENSE
Requires-Dist: Django>=3.2
Dynamic: author
Dynamic: author-email
Dynamic: classifier
Dynamic: description
Dynamic: description-content-type
Dynamic: home-page
Dynamic: keywords
Dynamic: license-file
Dynamic: project-url
Dynamic: requires-dist
Dynamic: requires-python
Dynamic: summary
